{
    "type": "minecraft:notice",
    "title": {
        "text": "祥兆玉石",
        "color": "dark_aqua",
        "italic": false
    },
    "external_title": {
        "text": ""
    },
    "body": [
        {
            "type": "minecraft:item",
            "item": {
                "id": "minecraft:emerald"
            },
            "show_decorations": false,
            "show_tooltip": false
        },
        {
            "type": "minecraft:plain_message",
            "contents": ["",{"color":"#CE9178","text":"-----神器特殊效果详情-----"},"\n",{"color":"gray","text":"- 放在背包内时生效"},"\n",{"color":"gold","bold":true,"text":"祥瑞"},"\n",{"color":"gray","text":"免疫负面效果"},"\n",{"color":"gold","bold":true,"text":"福兆"},"\n",{"color":"gray","text":"每60s获得10♥额外生命"},"\n",{"color":"gold","bold":true,"text":"抑灾"},"\n",{"color":"gray","text":"4格内敌对生物持续获得缓慢III"},"\n\n",{"color":"dark_gray","text":"一石可佑一方平安 沃土绵延 盈财万贯"},"\n",{"color":"dark_gray","text":"可惜此石只有一块 也只可庇佑一隅"},"\n",{"color":"dark_gray","text":"在漫长的夺石之争中"},"\n",{"color":"dark_gray","text":"战争荡尽了多少贪欲者的国库 沾染上了无数平民和权贵的鲜血"},"\n",{"color":"dark_gray","text":"一石可致一方涂炭 焦土千里 饿殍遍地"},"\n",{"color":"dark_gray","text":"怎知此石效用无害 又惹得全世哄抢"},"\n",{"color":"dark_gray","text":"在富饶的金山银山外 铁骑寻觅过多少无辜者的性命"},"\n",{"color":"dark_gray","text":"轻吹散了无数贪婪和自大的妄想"},"\n",{"color":"dark_gray","text":"只叹怀玉者无罪 怀玉有罪"}],
            "width": 480
        }
    ],
    "inputs": [],
    "can_close_with_escape": true,
    "action": {
        "label": {
            "text": "返回§6王之宝库",
            "color": "green"
        },
        "action": {
            "type": "minecraft:show_dialog",
            "dialog": "kards:paiku/wangzhibaoku/main"
        }
    }
}